__init__.py
check_tls/__init__.py
check_tls/main.py
check_tls/tls_checker.py
check_tls/web_server.py
check_tls/static/css/app.css
check_tls/static/js/app.js
check_tls/templates/index.html
check_tls/utils/__init__.py
check_tls/utils/cert_utils.py
check_tls/utils/crl_utils.py
check_tls/utils/crtsh_utils.py
check_tls/utils/dns_utils.py
check_tls/utils/ocsp_utils.py
check_tls/utils/security_utils.py
check_tls-1.8.0.dist-info/licenses/LICENSE
check_tls-1.8.0.dist-info/METADATA
check_tls-1.8.0.dist-info/WHEEL
check_tls-1.8.0.dist-info/entry_points.txt
check_tls-1.8.0.dist-info/top_level.txt
check_tls-1.8.0.dist-info/RECORD
