Metadata-Version: 2.4
Name: check-tls
Version: 1.8.0
Summary: A powerful, developer-friendly Python tool to analyze TLS/SSL certificates for any domain.
Author-email: "Grégoire Compagnon (obeone)" <obeone@obeone.org>
License: MIT License
Project-URL: Homepage, https://github.com/obeone/check-tls
Project-URL: Repository, https://github.com/obeone/check-tls
Requires-Python: >=3.9
License-File: LICENSE
Requires-Dist: cryptography<45.0.0,>=44.0.3
Requires-Dist: coloredlogs<16.0.0,>=15.0.1
Requires-Dist: flask<4.0.0,>=3.1.0
Requires-Dist: shtab<2.0.0,>=1.7.1
Requires-Dist: requests<3.0.0,>=2.31.0
Requires-Dist: dnspython<3.0.0,>=2.4.2
Provides-Extra: dev
Requires-Dist: setuptools_scm[toml]>=8; extra == "dev"
Dynamic: license-file
